sec_gemini/__init__.py
sec_gemini/api.proto
sec_gemini/client.py
sec_gemini/connection.py
sec_gemini/constants.py
sec_gemini/mcp.py
sec_gemini/session.py
sec_gemini/api_pb2.py
sec_gemini/api_pb2.pyi
sec_gemini/api_pb2_grpc.py
sec_gemini_3-0.1.1.dist-info/METADATA
sec_gemini_3-0.1.1.dist-info/WHEEL
sec_gemini_3-0.1.1.dist-info/RECORD
