Metadata-Version: 2.4
Name: sec-gemini-3
Version: 0.1.1
Summary: Python SDK for Sec-Gemini
Requires-Python: >=3.12
Requires-Dist: grpcio>=1.60.0
Requires-Dist: protobuf>=4.0.0
Requires-Dist: pydantic>=2.0.0
Requires-Dist: rich>=13.0.0
Provides-Extra: dev
Requires-Dist: pytest; extra == 'dev'
Requires-Dist: pytest-asyncio; extra == 'dev'
Requires-Dist: ruff; extra == 'dev'
